xweb_router.py
xweb_router-0.1.1.dist-info/METADATA
xweb_router-0.1.1.dist-info/RECORD
xweb_router-0.1.1.dist-info/WHEEL
xweb_router-0.1.1.dist-info/top_level.txt
