Metadata-Version: 2.1
Name: xweb-router
Version: 0.1.1
Summary: Router middleware for xweb.
Home-page: https://github.com/gaojiuli/xweb_router
Author: Jiuli Gao
Author-email: gaojiuli@gmail.com
License: MIT
Platform: any
Classifier: Development Status :: 3 - Alpha
Classifier: Intended Audience :: Developers
Classifier: License :: OSI Approved :: MIT License
Classifier: Topic :: Internet :: WWW/HTTP :: Dynamic Content :: CGI Tools/Libraries
Classifier: Topic :: Internet :: WWW/HTTP :: HTTP Servers
Classifier: Topic :: Software Development :: Libraries :: Application Frameworks
Classifier: Programming Language :: Python :: 3.6
Classifier: Programming Language :: Python :: 3.7
Requires-Dist: xweb
Requires-Dist: parse
